{"data":{"site":{"siteMetadata":{"title":"鹊巢小筑"}},"allMarkdownRemark":{"edges":[{"node":{"excerpt":"如果你不清楚如何判断 JS 函数中 this 的值是什么，也许你可以花些时间阅读一下这一篇博客。 在解释 值判断问题前，需要简单提一下另外一个同样重要，同样让 JS…","fields":{"slug":"/what-is-this/"},"frontmatter":{"date":"2019年 一月 30","title":"JavaScript函数中的this指的到底是什么？"}}},{"node":{"excerpt":"我是一个热爱 WEB 前端技术，同时也热爱分享的人。 过去的几年内，WEB 前端技术的发展真让人欣喜，CSS 中新的 Grid 布局在现代浏览器中的兼容情况非常良好，我们可以利用 Grid 实现之前无法或很难实现的设计，有时候甚至不用 Media Query…","fields":{"slug":"/hello-world/"},"frontmatter":{"date":"2019年 一月 28","title":"简单的自我介绍"}}}]}},"pageContext":{}}